mogreps_uk_dataset/__init__.py
mogreps_uk_dataset/_version.py
mogreps_uk_dataset/conn.py
mogreps_uk_dataset/mogreps_uk_cat.yaml
mogreps_uk_dataset/datasources/__init__.py
mogreps_uk_dataset/datasources/dataset.py
mogreps_uk_dataset/datasources/mogreps_uk.py
mogreps_uk_dataset/datasources/utils.py
mogreps_uk_dataset/zarrhypothetic/__init__.py
mogreps_uk_dataset/zarrhypothetic/zarrhypothetic.py
mogreps_uk_dataset-0.0.2.dist-info/LICENSE
mogreps_uk_dataset-0.0.2.dist-info/METADATA
mogreps_uk_dataset-0.0.2.dist-info/WHEEL
mogreps_uk_dataset-0.0.2.dist-info/entry_points.txt
mogreps_uk_dataset-0.0.2.dist-info/top_level.txt
mogreps_uk_dataset-0.0.2.dist-info/zip-safe
mogreps_uk_dataset-0.0.2.dist-info/RECORD
