Metadata-Version: 2.1
Name: mogreps-uk-dataset
Version: 0.0.2
Summary: DESCRIPTION
Home-page: https://github.com/informatics-lab/mogreps_uk_dataset
Author: Theo McCaie
Author-email: theo.mccaie@informaticslab.co.uk
License: UNKNOWN
Platform: UNKNOWN
Classifier: License :: OSI Approved :: GNU General Public License v3 (GPLv3)
Classifier: Operating System :: OS Independent
Classifier: Programming Language :: Python
Classifier: Programming Language :: Python :: 3
Classifier: Programming Language :: Python :: 3.4
Classifier: Programming Language :: Python :: 3.5
Classifier: Programming Language :: Python :: 3.6
Classifier: Topic :: Software Development :: Libraries :: Python Modules
Classifier: Natural Language :: English
Requires-Dist: numpy (>=1.11)
Requires-Dist: dask (>=1.0)
Requires-Dist: xarray
Requires-Dist: zarr (>=2)
Requires-Dist: adlfs
Requires-Dist: h5netcdf (>=0.8)
Requires-Dist: intake
Requires-Dist: toolz
